export_elements/version.py
export_elements/static/export_elements/images/accordion-arrow-2x.png
export_elements/static/export_elements/images/accordion-arrow.png
export_elements/static/export_elements/images/arrow-sprite.png
export_elements/static/export_elements/images/dfit-logo-white.png
export_elements/static/export_elements/images/great-logo-with-flag.png
export_elements/static/export_elements/images/icon-arrow-left.png
export_elements/static/export_elements/images/icon-calendar-2x.png
export_elements/static/export_elements/images/icon-calendar.png
export_elements/static/export_elements/images/icon-file-download-2x.png
export_elements/static/export_elements/images/icon-file-download.png
export_elements/static/export_elements/images/icon-important-2x.png
export_elements/static/export_elements/images/icon-important.png
export_elements/static/export_elements/images/icon-information-2x.png
export_elements/static/export_elements/images/icon-information.png
export_elements/static/export_elements/images/icon-locator-2x.png
export_elements/static/export_elements/images/icon-locator.png
export_elements/static/export_elements/images/icon-pointer-2x.png
export_elements/static/export_elements/images/icon-pointer-black-2x.png
export_elements/static/export_elements/images/icon-pointer-black.png
export_elements/static/export_elements/images/icon-pointer-indexed.png
export_elements/static/export_elements/images/icon-pointer.png
export_elements/static/export_elements/images/icon-search-2x.png
export_elements/static/export_elements/images/icon-search.png
export_elements/static/export_elements/images/player-icon-forward.png
export_elements/static/export_elements/images/player-icon-pause.png
export_elements/static/export_elements/images/player-icon-play.png
export_elements/static/export_elements/images/player-icon-rewind.png
export_elements/static/export_elements/images/player-icon-volume.png
export_elements-2.0.0.dist-info/DESCRIPTION.rst
export_elements-2.0.0.dist-info/METADATA
export_elements-2.0.0.dist-info/RECORD
export_elements-2.0.0.dist-info/WHEEL
export_elements-2.0.0.dist-info/metadata.json
export_elements-2.0.0.dist-info/top_level.txt
