Metadata-Version: 2.0
Name: export-elements
Version: 2.0.0
Summary: Wrapper around govuk elements.
Home-page: https://github.com/uktrade/export-elements
Author: Department for International Trade
Author-email: UNKNOWN
License: MIT
Platform: UNKNOWN
Classifier: Development Status :: 5 - Production/Stable
Classifier: Environment :: Web Environment
Classifier: Intended Audience :: Developers
Classifier: License :: OSI Approved :: MIT License
Classifier: Natural Language :: English
Classifier: Operating System :: OS Independent
Classifier: Topic :: Software Development :: Libraries :: Python Modules
